{"_type":"export","__export_format":4,"__export_date":"2024-10-04T16:13:15.437Z","__export_source":"insomnia.desktop.app:v10.0.0","resources":[{"_id":"req_c41b19329bc546f6be1e4cc6ad8aabc6","parentId":"wrk_528ce96745d64ff1a5d1e9927e511dc3","modified":1727712267287,"created":1727686548689,"url":"http://51.83.27.198:9080/app/contrats/auth/getListeBanques","name":"http://51.83.27.198:9080/app/contrats/auth/getListeBanques","description":"","method":"POST","body":{"mimeType":"application/x-www-form-urlencoded","params":[{"name":"client_id","value":"banque-front"},{"name":"grant_type","value":"password"},{"name":"baseUrl","value":"http://51.83.27.198:9080/"},{"name":"typeProfil","value":"BO"},{"name":"canal","value":"Web"}]},"parameters":[],"headers":[{"name":"Accept","value":"*/*"},{"name":"Accept-Language","value":"en-US,en;q=0.9,fr;q=0.8"},{"name":"Connection","value":"keep-alive"},{"name":"Content-Type","value":"application/x-www-form-urlencoded"},{"name":"Origin","value":"http://51.83.27.198:3001"},{"name":"Referer","value":"http://51.83.27.198:3001/"},{"name":"User-Agent","value":"Mozilla/5.0 (Macintosh; Intel Mac OS X 10_15_7) AppleWebKit/537.36 (KHTML, like Gecko) Chrome/129.0.0.0 Safari/537.36"}],"authentication":{},"preRequestScript":"","metaSortKey":-1727686548689,"isPrivate":false,"afterResponseScript":"\n","settingStoreCookies":true,"settingSendCookies":true,"settingDisableRenderRequestBody":false,"settingEncodeUrl":true,"settingRebuildPath":true,"settingFollowRedirects":"global","_type":"request"},{"_id":"wrk_528ce96745d64ff1a5d1e9927e511dc3","parentId":null,"modified":1728040260988,"created":1728040260988,"name":"contracts-service","description":"","scope":"collection","_type":"workspace"},{"_id":"env_6cec72f5e3574ca1b60370bbb719fa30","parentId":"wrk_528ce96745d64ff1a5d1e9927e511dc3","modified":1727712270259,"created":1726245876678,"name":"Base Environment","data":{},"dataPropertyOrder":{},"color":null,"isPrivate":false,"metaSortKey":1726245876678,"_type":"environment"},{"_id":"jar_911045d4a5894cd7b1e62fdebb676821","parentId":"wrk_528ce96745d64ff1a5d1e9927e511dc3","modified":1727712270259,"created":1726245876679,"name":"Default Jar","cookies":[],"_type":"cookie_jar"}]}
